mutwo/midi_converters/__init__.py
mutwo/midi_converters/backends.py
mutwo/midi_converters/configurations.py
mutwo/midi_converters/constants.py
mutwo/midi_converters/frontends.py
mutwo/midi_version/__init__.py
mutwo.midi-0.12.1.dist-info/LICENSE
mutwo.midi-0.12.1.dist-info/METADATA
mutwo.midi-0.12.1.dist-info/WHEEL
mutwo.midi-0.12.1.dist-info/top_level.txt
mutwo.midi-0.12.1.dist-info/RECORD
